pantsbuild.pants.contrib.scalajs-1.28.0-py3.6-nspkg.pth
pants/contrib/scalajs/__init__.py
pants/contrib/scalajs/register.py
pants/contrib/scalajs/target_types.py
pants/contrib/scalajs/subsystems/__init__.py
pants/contrib/scalajs/subsystems/scala_js_platform.py
pants/contrib/scalajs/targets/__init__.py
pants/contrib/scalajs/targets/scala_js_binary.py
pants/contrib/scalajs/targets/scala_js_library.py
pants/contrib/scalajs/targets/scala_js_target.py
pants/contrib/scalajs/tasks/__init__.py
pants/contrib/scalajs/tasks/scala_js_link.py
pants/contrib/scalajs/tasks/scala_js_zinc_compile.py
pantsbuild.pants.contrib.scalajs-1.28.0.dist-info/METADATA
pantsbuild.pants.contrib.scalajs-1.28.0.dist-info/WHEEL
pantsbuild.pants.contrib.scalajs-1.28.0.dist-info/entry_points.txt
pantsbuild.pants.contrib.scalajs-1.28.0.dist-info/namespace_packages.txt
pantsbuild.pants.contrib.scalajs-1.28.0.dist-info/top_level.txt
pantsbuild.pants.contrib.scalajs-1.28.0.dist-info/zip-safe
pantsbuild.pants.contrib.scalajs-1.28.0.dist-info/RECORD
